{
  "posts": [
    {
      "title": "Test post",
      "categories": "Post post post post ",
      "content": "Post post post post\n",
      "id": 1
    }
  ],
  "students": [
    {
      "id": 1,
      "name": "some comment",
      "notes": "Notes",
      "courses": [
        1,
        2,
        3
      ]
    }
  ],
  "faculty": [
    {
      "id": 1,
      "body": "some comment"
    }
  ],
  "recruits": [],
  "courses": [
    {
      "id": 1,
      "subject": "course 1",
      "teacherId": 1
    }
  ],
  "profile": {
    "name": "typicode"
  }
}